CHANGELOG
LICENSE
MANIFEST.in
README.rst
setup.py
docs/Makefile
docs/source/apple_notifications.rst
docs/source/conf.py
docs/source/getting_started.rst
docs/source/index.rst
pypusher/__init__.py
pypusher/pypusher.py
pypusher/tests.py
pypusher.egg-info/PKG-INFO
pypusher.egg-info/SOURCES.txt
pypusher.egg-info/dependency_links.txt
pypusher.egg-info/not-zip-safe
pypusher.egg-info/requires.txt
pypusher.egg-info/top_level.txt