Metadata-Version: 1.1
Name: pypusher
Version: 0.1.0
Summary: pypusher pushes stuff from Python
Home-page: http://github.com/idlesign/pypusher
Author: Igor 'idle sign' Starikov
Author-email: idlesign@yandex.ru
License: UNKNOWN
Platform: UNKNOWN
Classifier: Development Status :: 4 - Beta
Classifier: Intended Audience :: Developers
Classifier: License :: OSI Approved :: BSD License
Classifier: Operating System :: OS Independent
Classifier: Programming Language :: Python
Classifier: Programming Language :: Python :: 3
Classifier: Programming Language :: Python :: 3.3
